{
  "data": [
    {"id":1,
    "Project_Name":"Esoft",
    "Status":"Male",
    "LastUpdate":"2/22/2022",
    "Resources":"M","ProjectTimiline":"3/11/2022","Estimation":"$5.43"},
    {"id":2,
    "Project_Name":"Aasrts",
    "Status":"Female",
    "LastUpdate":"12/6/2021",
    "Resources":"M","ProjectTimiline":"2/15/2022","Estimation":"$3.77"},
    {"id":3,
    "Project_Name":"TrZap",
    "Status":"Female",
    "LastUpdate":"11/16/2021",
    "Resources":"M","ProjectTimiline":"4/23/2022","Estimation":"$8.34"},
    {"id":4,
    "Project_Name":"Latlux",
    "Status":"Agender",
    "LastUpdate":"7/10/2022",
    "Resources":"M","ProjectTimiline":"5/20/2022","Estimation":"$8.91"},
    {"id":5,
    "Project_Name":"Vagram",
    "Status":"Female",
    "LastUpdate":"10/18/2022",
    "Resources":"F",
    "ProjectTimiline":"4/20/2022",
    "Estimation":"$8.76"},
    {"id":6,
    "Project_Name":"Otcom",
    "Status":"Female",
    "LastUpdate":"12/13/2021",
    "Resources":"M",
    "ProjectTimiline":"2/21/2022",
    "Estimation":"$9.76"},
    {"id":7,
    "Project_Name":"Bitwolf",
    "Status":"Female","LastUpdate":"8/11/2022","Resources":"F","ProjectTimiline":"10/1/2022","Estimation":"$4.25"},
    {"id":8,
    "Project_Name":"Home Ing","Status":"Female","LastUpdate":"6/14/2022","Resources":"M","ProjectTimiline":"11/6/2022","Estimation":"$9.94"},
    {"id":9,"Project_Name":"Duobam","Status":"Male","LastUpdate":"11/11/2022","Resources":"M","ProjectTimiline":"12/17/2021","Estimation":"$9.75"},
    {"id":10,"Project_Name":"Domainer","Status":"Male","LastUpdate":"2/9/2022","Resources":"M","ProjectTimiline":"12/22/2021","Estimation":"$5.05"},
    {"id":11,"Project_Name":"It","Status":"Female","LastUpdate":"12/28/2021","Resources":"F","ProjectTimiline":"8/13/2022","Estimation":"$9.67"},
    {"id":12,"Project_Name":"Lotstring","Status":"Male","LastUpdate":"11/11/2021","Resources":"F","ProjectTimiline":"12/3/2021","Estimation":"$5.47"},
    {"id":13,"Project_Name":"Pannier","Status":"Female","LastUpdate":"4/9/2022","Resources":"M","ProjectTimiline":"6/30/2022","Estimation":"$7.42"},
    {"id":14,"Project_Name":"Andalax","Status":"Male","LastUpdate":"12/22/2021","Resources":"F","ProjectTimiline":"4/4/2022","Estimation":"$4.52"},
    {"id":15,"Project_Name":"Fixflex","Status":"Female","LastUpdate":"10/12/2022","Resources":"F","ProjectTimiline":"2/25/2022","Estimation":"$7.92"},
    {"id":16,"Project_Name":"Y-find","Status":"Female","LastUpdate":"2/17/2022","Resources":"F","ProjectTimiline":"3/1/2022","Estimation":"$7.47"},
    {"id":17,"Project_Name":"Matsoft","Status":"Bigender","LastUpdate":"1/8/2022","Resources":"M","ProjectTimiline":"3/16/2022","Estimation":"$5.43"},
    {"id":18,"Project_Name":"Fintone","Status":"Female","LastUpdate":"5/17/2022","Resources":"M","ProjectTimiline":"2/4/2022","Estimation":"$9.86"},
    {"id":19,"Project_Name":"Toughjoyfax","Status":"Female","LastUpdate":"6/10/2022","Resources":"M","ProjectTimiline":"6/6/2022","Estimation":"$9.20"},
    {"id":20,"Project_Name":"Bitchip","Status":"Bigender","LastUpdate":"6/11/2022","Resources":"F","ProjectTimiline":"10/7/2022","Estimation":"$1.53"},
    {"id":21,"Project_Name":"Andalax","Status":"Agender","LastUpdate":"5/22/2022","Resources":"F","ProjectTimiline":"7/13/2022","Estimation":"$4.86"},
    {"id":22,"Project_Name":"Job","Status":"Male","LastUpdate":"4/21/2022","Resources":"M","ProjectTimiline":"2/4/2022","Estimation":"$3.63"},
    {"id":23,"Project_Name":"Zamit","Status":"Male","LastUpdate":"3/8/2022","Resources":"M","ProjectTimiline":"5/26/2022","Estimation":"$7.61"},
    {"id":24,"Project_Name":"Subin","Status":"Female","LastUpdate":"11/19/2021","Resources":"M","ProjectTimiline":"6/4/2022","Estimation":"$2.18"},
    {"id":25,"Project_Name":"Bitchip","Status":"Female","LastUpdate":"7/25/2022","Resources":"M","ProjectTimiline":"10/25/2022","Estimation":"$4.77"},
    {"id":26,"Project_Name":"Zamit","Status":"Female","LastUpdate":"2/5/2022","Resources":"F","ProjectTimiline":"3/4/2022","Estimation":"$9.75"},
    {"id":27,"Project_Name":"Rank","Status":"Male","LastUpdate":"4/18/2022","Resources":"F","ProjectTimiline":"8/14/2022","Estimation":"$2.89"},
    {"id":28,"Project_Name":"Kanlam","Status":"Male","LastUpdate":"4/10/2022","Resources":"M","ProjectTimiline":"12/30/2021","Estimation":"$1.77"},
    {"id":29,"Project_Name":"Ronstring","Status":"Female","LastUpdate":"1/21/2022","Resources":"M","ProjectTimiline":"6/9/2022","Estimation":"$1.88"},
    {"id":30,"Project_Name":"Aerified","Status":"Female","LastUpdate":"6/22/2022","Resources":"M","ProjectTimiline":"1/4/2022","Estimation":"$1.29"},
    {"id":31,"Project_Name":"Keylex","Status":"Bigender","LastUpdate":"11/23/2021","Resources":"F","ProjectTimiline":"1/16/2022","Estimation":"$9.88"},
    {"id":32,"Project_Name":"Stringtough","Status":"Female","LastUpdate":"3/15/2022","Resources":"F","ProjectTimiline":"11/15/2021","Estimation":"$2.64"},
    {"id":33,"Project_Name":"Treeflex","Status":"Male","LastUpdate":"5/14/2022","Resources":"M","ProjectTimiline":"3/1/2022","Estimation":"$8.21"},
    {"id":34,"Project_Name":"Ventosanzap","Status":"Female","LastUpdate":"3/21/2022","Resources":"M","ProjectTimiline":"11/11/2022","Estimation":"$0.89"},
    {"id":35,"Project_Name":"Solarbreeze","Status":"Male","LastUpdate":"2/21/2022","Resources":"M","ProjectTimiline":"11/4/2022","Estimation":"$4.44"},
    {"id":36,"Project_Name":"Aerified","Status":"Male","LastUpdate":"7/17/2022","Resources":"F","ProjectTimiline":"2/27/2022","Estimation":"$2.21"},
    {"id":37,"Project_Name":"Zaam-Dox","Status":"Male","LastUpdate":"9/9/2022","Resources":"M","ProjectTimiline":"4/15/2022","Estimation":"$7.30"},
    {"id":38,"Project_Name":"Zontrax","Status":"Female","LastUpdate":"4/11/2022","Resources":"M","ProjectTimiline":"12/20/2021","Estimation":"$6.20"},
    {"id":39,"Project_Name":"Redhold","Status":"Female","LastUpdate":"2/8/2022","Resources":"F","ProjectTimiline":"1/10/2022","Estimation":"$4.57"},
    {"id":40,"Project_Name":"Prodder","Status":"Male","LastUpdate":"9/13/2022","Resources":"F","ProjectTimiline":"7/11/2022","Estimation":"$2.51"},
    {"id":41,"Project_Name":"Konklab","Status":"Male","LastUpdate":"12/11/2021","Resources":"F","ProjectTimiline":"2/27/2022","Estimation":"$9.15"},
    {"id":42,"Project_Name":"Sonair","Status":"Male","LastUpdate":"12/9/2021","Resources":"F","ProjectTimiline":"4/17/2022","Estimation":"$9.27"},
    {"id":43,"Project_Name":"Asoka","Status":"Male","LastUpdate":"2/8/2022","Resources":"F","ProjectTimiline":"3/30/2022","Estimation":"$1.08"},
    {"id":44,"Project_Name":"Matsoft","Status":"Non-binary","LastUpdate":"3/8/2022","Resources":"M","ProjectTimiline":"3/15/2022","Estimation":"$6.90"},
    {"id":45,"Project_Name":"Andalax","Status":"Female","LastUpdate":"12/25/2021","Resources":"F","ProjectTimiline":"1/29/2022","Estimation":"$7.01"},
    {"id":46,"Project_Name":"Viva","Status":"Male","LastUpdate":"11/21/2021","Resources":"F","ProjectTimiline":"8/18/2022","Estimation":"$1.62"},
    {"id":47,"Project_Name":"Zathin","Status":"Male","LastUpdate":"7/30/2022","Resources":"M","ProjectTimiline":"6/15/2022","Estimation":"$8.30"},
    {"id":48,"Project_Name":"Duobam","Status":"Bigender","LastUpdate":"2/16/2022","Resources":"F","ProjectTimiline":"4/25/2022","Estimation":"$6.73"},
    {"id":49,"Project_Name":"Y-find","Status":"Agender","LastUpdate":"3/28/2022","Resources":"M","ProjectTimiline":"4/30/2022","Estimation":"$9.53"},
    {"id":50,"Project_Name":"Otcom","Status":"Female","LastUpdate":"4/13/2022","Resources":"M","ProjectTimiline":"1/22/2022","Estimation":"$7.94"}]
}
